dora_distil_whisper/__init__.py
dora_distil_whisper/main.py
dora_distil_whisper-0.4.1.dist-info/METADATA
dora_distil_whisper-0.4.1.dist-info/WHEEL
dora_distil_whisper-0.4.1.dist-info/entry_points.txt
dora_distil_whisper-0.4.1.dist-info/top_level.txt
dora_distil_whisper-0.4.1.dist-info/RECORD
