Metadata-Version: 2.4
Name: dora-distil-whisper
Version: 0.4.1
Summary: Dora dora-distil-whisper
Author-email: Haixuan Xavier Tao <tao.xavier@outlook.com>, Enzo Le Van <dev@enzo-le-van.fr>
License: MIT
Requires-Python: >=3.9
Requires-Dist: dora-rs>=0.3.9
Requires-Dist: numpy<2.0.0
Requires-Dist: pyarrow>=5.0.0
Requires-Dist: transformers>=4.0.0
Requires-Dist: accelerate>=0.29.2
Requires-Dist: torch>=2.7.0
Requires-Dist: torchvision>=0.22
Requires-Dist: torchaudio>=2.7.0
Requires-Dist: modelscope>=1.18.1
Requires-Dist: mlx-whisper>=0.4.1; sys_platform == "darwin"
